README.rst
setup.py
easy_logger/__init__.py
easy_logger/config.py
easy_logger.egg-info/PKG-INFO
easy_logger.egg-info/SOURCES.txt
easy_logger.egg-info/dependency_links.txt
easy_logger.egg-info/top_level.txt
examples/__init__.py
examples/test_api.py
tests/__init__.py