Metadata-Version: 1.0
Name: easy-logger
Version: 1.0
Summary: A python package for logging easily
Home-page: https://github.com/omsobliga/easy-logger
Author: omsobliga
Author-email: omsobliga@gmail.com
License: MIT
Platform: UNKNOWN
